./.gitignore
./PKG-INFO
./README.md
./pyproject.toml
./vision_agents/plugins/cartesia/__init__.py
./vision_agents/plugins/cartesia/tts.py
vision_agents_plugins_cartesia-0.2.10.dist-info/METADATA
vision_agents_plugins_cartesia-0.2.10.dist-info/WHEEL
vision_agents_plugins_cartesia-0.2.10.dist-info/RECORD
