Metadata-Version: 2.4
Name: vision-agents-plugins-cartesia
Version: 0.2.10
Summary: Cartesia TTS integration for Vision Agents
Project-URL: Documentation, https://visionagents.ai/
Project-URL: Website, https://visionagents.ai/
Project-URL: Source, https://github.com/GetStream/Vision-Agents
License-Expression: MIT
Keywords: AI,TTS,agents,cartesia,text-to-speech,voice agents
Requires-Python: >=3.10
Requires-Dist: cartesia>=2.0.15
Requires-Dist: vision-agents
